README.rst
setup.py
evaluator/__init__.py
evaluator/evaluator.py
evaluator/hand.py
evaluator/main.py
pypoker.egg-info/PKG-INFO
pypoker.egg-info/SOURCES.txt
pypoker.egg-info/dependency_links.txt
pypoker.egg-info/entry_points.txt
pypoker.egg-info/namespace_packages.txt
pypoker.egg-info/requires.txt
pypoker.egg-info/top_level.txt