Metadata-Version: 1.1
Name: pypoker
Version: 0.0.1a
Summary: Scaffolding generator for Python app using cliff
Home-page: https://github.com/jamesbeedy/pypoker
Author: James Beedy
Author-email: jamesbeedy@gmail.com
License: UNKNOWN
Download-URL: https://github.com/jamesbeedy/pypoker/archive/v0.0.1a.tar.gz
Keywords: sample setuptools development
Platform: Any
Classifier: Development Status :: 3 - Alpha
Classifier: Intended Audience :: Developers
Classifier: Topic :: Software Development :: Build Tools
Classifier: License :: OSI Approved :: Apache Software License
Classifier: Programming Language :: Python
Classifier: Programming Language :: Python :: 2
Classifier: Programming Language :: Python :: 2.7
Classifier: Programming Language :: Python :: 3
Classifier: Programming Language :: Python :: 3.2
Classifier: Intended Audience :: Developers
Classifier: Environment :: Console
